{
  "cursos": [
    {
      "id": 1,
      "nome": "Angular"
    },
    {
      "id": 2,
      "nome": "React"
    },
    {
      "id": 3,
      "nome": "Java"
    },
    {
      "nome": "VueJS",
      "id": 4
    },
    {
      "nome": "Spring API",
      "id": 5
    },
    {
      "nome": "Ruby",
      "id": 6
    },
    {
      "nome": "dada",
      "id": 7
    },
    {
      "nome": "adadad",
      "id": 8
    },
    {
      "nome": "dada",
      "id": 9
    },
    {
      "nome": "dadadawdaw",
      "id": 10
    },
    {
      "nome": "dadawdawdaw",
      "id": 11
    },
    {
      "nome": "Material 5",
      "id": 12
    }
  ]
}